pyautoguinodelays/.idea/.gitignore
pyautoguinodelays/.idea/.name
pyautoguinodelays/.idea/inspectionProfiles/profiles_settings.xml
pyautoguinodelays/.idea/misc.xml
pyautoguinodelays/.idea/modules.xml
pyautoguinodelays/.idea/pyautoguinodelays.iml
pyautoguinodelays/.idea/workspace.xml
pyautoguinodelays/__init__.py
pyautoguinodelays/__main__.py
pyautoguinodelays/_pyautogui_win.py
pyautoguinodelays/_pyautogui_x11.py
pyautoguinodelays/_window_win.py
pyautoguinodelays/dist/pyautoguinodelays-0.1.0.tar.gz
pyautoguinodelays/dist/pyautoguinodelays-0.2.0.tar.gz
pyautoguinodelays/poetry.lock
pyautoguinodelays/pyproject.toml
pyautoguinodelays/README.md
pyautoguinodelays/screenshotUtil.py
pyautoguinodelays/tweens.py
pyautoguinodelays-0.2.1.dist-info/METADATA
pyautoguinodelays-0.2.1.dist-info/WHEEL
pyautoguinodelays-0.2.1.dist-info/RECORD
