Metadata-Version: 2.3
Name: pyautoguinodelays
Version: 0.2.1
Summary: OSRS Bots
License: MIT?
Author: someangrylemons
Author-email: 62520125+someangrylemons@users.noreply.github.com
Requires-Python: >=3.13
Classifier: License :: Other/Proprietary License
Classifier: Programming Language :: Python :: 3
Classifier: Programming Language :: Python :: 3.13
